cluster_arena/__init__.py
cluster_arena/main.py
cluster_arena-1.0.2.dist-info/METADATA
cluster_arena-1.0.2.dist-info/WHEEL
cluster_arena-1.0.2.dist-info/top_level.txt
cluster_arena-1.0.2.dist-info/RECORD
