Metadata-Version: 2.1
Name: cluster-arena
Version: 1.0.2
Summary: A Python client for the Cluster Arena API
Home-page: UNKNOWN
Author: Kanhaiya
Author-email: kanhaiya2778@gmail.com
License: UNKNOWN
Platform: UNKNOWN
Classifier: Programming Language :: Python :: 3
Classifier: License :: OSI Approved :: MIT License
Classifier: Operating System :: OS Independent
Requires-Python: >=3.6
Requires-Dist: pydantic>=1.8.1
Requires-Dist: requests>=2.25.1
